{
	"credit": "Made with Blockbench",
	"texture_size": [128, 128],
	"textures": {
		"0": "./relic_speaker",
		"particle": "./relic_speaker"
	},
	"elements": [
		{
			"from": [3, 0, 7],
			"to": [13, 0.5, 9],
			"rotation": {"angle": 0, "axis": "x", "origin": [8, 2, 8]},
			"faces": {
				"north": {"uv": [5.75, 5.75, 8.25, 5.875], "texture": "#0"},
				"east": {"uv": [0, 3, 0.5, 3.625], "texture": "#0"},
				"south": {"uv": [5.75, 5.5, 8.25, 5.625], "texture": "#0"},
				"west": {"uv": [0, 3, 0.5, 3.625], "texture": "#0"},
				"up": {"uv": [0, 0, 16, 3], "texture": "#0"},
				"down": {"uv": [0, 0, 16, 3.5], "texture": "#0"}
			}
		},
		{
			"from": [3, 4.32843, 7],
			"to": [13, 4.82843, 9],
			"rotation": {"angle": 0, "axis": "x", "origin": [8, 2.92843, 8]},
			"faces": {
				"north": {"uv": [5.75, 5.625, 8.25, 5.75], "texture": "#0"},
				"east": {"uv": [0, 3, 0.5, 3.625], "texture": "#0"},
				"south": {"uv": [0, 5.875, 2.5, 6], "texture": "#0"},
				"west": {"uv": [0, 3, 0.5, 3.625], "texture": "#0"},
				"up": {"uv": [0, 0, 16, 3.5], "texture": "#0"},
				"down": {"uv": [0, 0, 16, 3], "texture": "#0"}
			}
		},
		{
			"from": [3, 0.12132, 7.29289],
			"to": [13, 0.62132, 9.29289],
			"rotation": {"angle": -45, "axis": "x", "origin": [8, 2.12132, 8.29289]},
			"faces": {
				"north": {"uv": [5.75, 5.875, 8.25, 6], "texture": "#0"},
				"east": {"uv": [0, 3, 0.5, 3.625], "texture": "#0"},
				"south": {"uv": [0, 6, 2.5, 6.125], "texture": "#0"},
				"west": {"uv": [0, 3, 0.5, 3.625], "texture": "#0"},
				"up": {"uv": [0, 0, 16, 3], "texture": "#0"},
				"down": {"uv": [0, 0, 16, 3.5], "texture": "#0"}
			}
		},
		{
			"from": [3, 4.20711, 7.29289],
			"to": [13, 4.70711, 9.29289],
			"rotation": {"angle": 45, "axis": "x", "origin": [8, 2.70711, 8.29289]},
			"faces": {
				"north": {"uv": [5.75, 6, 8.25, 6.125], "texture": "#0"},
				"east": {"uv": [0, 3, 0.5, 3.625], "texture": "#0"},
				"south": {"uv": [0, 6.125, 2.5, 6.25], "texture": "#0"},
				"west": {"uv": [0, 3, 0.5, 3.625], "texture": "#0"},
				"up": {"uv": [0, 0.5, 16, 4], "texture": "#0"},
				"down": {"uv": [4.75, 2, 7.25, 2.5], "texture": "#0"}
			}
		},
		{
			"from": [3, 1.41421, 9.91421],
			"to": [13, 3.41421, 10.41421],
			"rotation": {"angle": 0, "axis": "x", "origin": [8, 2.41421, 8.41421]},
			"faces": {
				"north": {"uv": [0, 0, 16, 3], "texture": "#0"},
				"east": {"uv": [0, 3, 0.5, 3.625], "texture": "#0"},
				"south": {"uv": [0, 0, 16, 3.5], "texture": "#0"},
				"west": {"uv": [0, 3, 0.5, 3.625], "texture": "#0"},
				"up": {"uv": [5.75, 6.125, 8.25, 6.25], "texture": "#0"},
				"down": {"uv": [0, 6.25, 2.5, 6.375], "texture": "#0"}
			}
		},
		{
			"from": [3, 1.41421, 5.58579],
			"to": [13, 3.41421, 6.08579],
			"rotation": {"angle": 0, "axis": "x", "origin": [8, 2.41421, 7.58579]},
			"faces": {
				"north": {"uv": [0, 1, 16, 4.5], "texture": "#0"},
				"east": {"uv": [0, 3, 0.5, 3.625], "texture": "#0"},
				"south": {"uv": [0, 0, 16, 3], "texture": "#0"},
				"west": {"uv": [0, 3, 0.5, 3.625], "texture": "#0"},
				"up": {"uv": [5.75, 6.25, 8.25, 6.375], "texture": "#0"},
				"down": {"uv": [0, 6.375, 2.5, 6.5], "texture": "#0"}
			}
		},
		{
			"from": [3, 1.12132, 5.70711],
			"to": [13, 3.12132, 6.20711],
			"rotation": {"angle": -45, "axis": "x", "origin": [8, 2.12132, 7.70711]},
			"faces": {
				"north": {"uv": [0, 0.5, 16, 4], "texture": "#0"},
				"east": {"uv": [0, 3, 0.5, 3.625], "texture": "#0"},
				"south": {"uv": [0, 0, 16, 3], "texture": "#0"},
				"west": {"uv": [0, 3, 0.5, 3.625], "texture": "#0"},
				"up": {"uv": [5.75, 6.375, 8.25, 6.5], "texture": "#0"},
				"down": {"uv": [0, 6.5, 2.5, 6.625], "texture": "#0"}
			}
		},
		{
			"from": [3, 1.70711, 5.70711],
			"to": [13, 3.70711, 6.30711],
			"rotation": {"angle": 45, "axis": "x", "origin": [8, 2.70711, 7.70711]},
			"faces": {
				"north": {"uv": [0, 0, 16, 3], "texture": "#0"},
				"east": {"uv": [0, 3, 0.5, 3.625], "texture": "#0"},
				"south": {"uv": [0, 0, 16, 3], "texture": "#0"},
				"west": {"uv": [0, 3, 0.5, 3.625], "texture": "#0"},
				"up": {"uv": [5.75, 6.5, 8.25, 6.625], "texture": "#0"},
				"down": {"uv": [0, 6.625, 2.5, 6.75], "texture": "#0"}
			}
		},
		{
			"from": [7.7, 2.20711, 5.60711],
			"to": [8.5, 3.00711, 5.70711],
			"rotation": {"angle": 45, "axis": "x", "origin": [8, 2.70711, 7.70711]},
			"faces": {
				"north": {"uv": [5, 7, 15.75, 16], "texture": "#0"},
				"east": {"uv": [13.5, 7, 15.75, 9.125], "texture": "#0"},
				"south": {"uv": [3.25, 6.25, 3.5, 6.5], "texture": "#0"},
				"west": {"uv": [13.5, 7, 15.75, 9.125], "texture": "#0"},
				"up": {"uv": [13.5, 7, 15.75, 9.125], "texture": "#0"},
				"down": {"uv": [13.5, 7, 15.75, 9.125], "texture": "#0"}
			}
		},
		{
			"from": [3.3, 0.2, 7],
			"to": [12.7, 4.5, 9],
			"faces": {
				"north": {"uv": [0, 0, 2.375, 1.125], "texture": "#0"},
				"east": {"uv": [2, 6, 3.5, 10.625], "texture": "#0"},
				"south": {"uv": [0, 1.125, 2.375, 2.25], "texture": "#0"},
				"west": {"uv": [2, 6, 3.5, 10.625], "texture": "#0"},
				"up": {"uv": [0, 5.375, 2.375, 5.875], "texture": "#0"},
				"down": {"uv": [2.375, 5.375, 4.75, 5.875], "texture": "#0"}
			}
		},
		{
			"from": [3.3, 0.7, 6.5],
			"to": [12.7, 4.1, 7],
			"faces": {
				"north": {"uv": [0, 2.25, 2.375, 3.125], "texture": "#0"},
				"east": {"uv": [4, 6.4375, 3.375, 9.8125], "texture": "#0"},
				"south": {"uv": [2.375, 2.375, 4.75, 3.25], "texture": "#0"},
				"west": {"uv": [3, 6.4375, 3.625, 9.8125], "texture": "#0"},
				"up": {"uv": [0, 6.75, 2.375, 6.875], "texture": "#0"},
				"down": {"uv": [2.375, 6.75, 4.75, 6.875], "texture": "#0"}
			}
		},
		{
			"from": [3.3, 0.7, 9],
			"to": [12.7, 4.2, 9.5],
			"faces": {
				"north": {"uv": [4.75, 2.375, 2.375, 3.25], "texture": "#0"},
				"east": {"uv": [3, 6.4375, 3.625, 9.8125], "texture": "#0"},
				"south": {"uv": [2.375, 2.25, 0, 3.125], "texture": "#0"},
				"west": {"uv": [4, 6.4375, 3.375, 9.8125], "texture": "#0"},
				"up": {"uv": [0, 6.875, 2.375, 6.75], "texture": "#0"},
				"down": {"uv": [2.375, 6.875, 4.75, 6.75], "texture": "#0"}
			}
		},
		{
			"from": [3.3, 1.1, 6],
			"to": [12.7, 3.8, 6.5],
			"faces": {
				"north": {"uv": [2.375, 3.25, 4.75, 3.875], "texture": "#0"},
				"east": {"uv": [4.5, 7, 5.0625, 9.33738], "texture": "#0"},
				"south": {"uv": [0, 3.75, 2.375, 4.375], "texture": "#0"},
				"west": {"uv": [4.5, 7, 5.0625, 9.83738], "rotation": 180, "texture": "#0"},
				"up": {"uv": [2.375, 6.875, 4.75, 7], "texture": "#0"},
				"down": {"uv": [4.75, 6.875, 7.125, 7], "texture": "#0"}
			}
		},
		{
			"from": [3.3, 1.2, 9.5],
			"to": [12.7, 3.8, 10],
			"faces": {
				"north": {"uv": [2.375, 3.75, 0, 4.375], "texture": "#0"},
				"east": {"uv": [4.5, 6.9375, 5.0625, 9.77488], "rotation": 180, "texture": "#0"},
				"south": {"uv": [4.75, 3.25, 2.375, 3.875], "texture": "#0"},
				"west": {"uv": [4.5625, 6.9375, 4, 9.775], "rotation": 180, "texture": "#0"},
				"up": {"uv": [2.375, 7, 4.75, 6.875], "texture": "#0"},
				"down": {"uv": [4.75, 7, 7.125, 6.875], "texture": "#0"}
			}
		}
	],
	"display": {
		"thirdperson_righthand": {
			"rotation": [15, 0, 0],
			"translation": [0, 4.25, 1.25],
			"scale": [0.9, 0.9, 0.9]
		},
		"thirdperson_lefthand": {
			"rotation": [39, 0, 0],
			"translation": [0, 5, 4]
		},
		"firstperson_righthand": {
			"rotation": [0, 107, -3],
			"translation": [-0.75, 7.75, 1],
			"scale": [0.7, 0.7, 0.7]
		},
		"firstperson_lefthand": {
			"rotation": [0, 98, 0],
			"translation": [-0.25, 8.75, 1.25],
			"scale": [0.7, 0.7, 0.7]
		},
		"ground": {
			"translation": [0, 4.25, 0]
		},
		"gui": {
			"rotation": [15, -143, -18],
			"translation": [-2, 7.25, 0],
			"scale": [1.5, 1.5, 1.5]
		},
		"head": {
			"translation": [0, 14.25, -1.5]
		},
		"fixed": {
			"translation": [0, 8, -2.75],
			"scale": [1.5, 1.5, 1.5]
		}
	}
}
