{
	"credit": "Made with Blockbench",
	"textures": {
		"texture": "./monsterbook"
	},
	"elements": [
		{
			"from": [1.6634, 0.1584, 1.6634],
			"to": [10.99673, 0.49173, 13.99673],
			"faces": {
				"north": {"uv": [0, 8.76923, 4.30769, 8.92308], "rotation": 180, "texture": "#texture"},
				"east": {"uv": [4.15385, 8.92308, 4.30769, 2.92308], "rotation": 90, "texture": "#texture"},
				"south": {"uv": [0, 8.76923, 4.30769, 8.92308], "texture": "#texture"},
				"west": {"uv": [4.15385, 8.92308, 4.30769, 2.92308], "rotation": 90, "texture": "#texture"},
				"up": {"uv": [4.30769, 3.07692, 8.76923, 8.76923], "texture": "#texture"},
				"down": {"uv": [4.30769, 3.07692, 8.76923, 8.76923], "texture": "#texture"}
			}
		},
		{
			"from": [1.6634, 3.1584, 1.6634],
			"to": [10.99673, 3.49173, 13.99673],
			"faces": {
				"north": {"uv": [0, 8.76923, 4.30769, 8.92308], "rotation": 180, "texture": "#texture"},
				"east": {"uv": [4.15385, 2.92308, 4.30769, 8.92308], "rotation": 90, "texture": "#texture"},
				"south": {"uv": [0, 8.76923, 4.30769, 8.92308], "texture": "#texture"},
				"west": {"uv": [4.15385, 2.92308, 4.30769, 8.92308], "rotation": 90, "texture": "#texture"},
				"up": {"uv": [0, 2.92308, 4.30769, 8.92308], "texture": "#texture"},
				"down": {"uv": [4.30769, 3.07692, 8.76923, 8.76923], "texture": "#texture"}
			}
		},
		{
			"from": [0.9878, 1.7318, 1.6634],
			"to": [1.30463, 3.47437, 14.01984],
			"rotation": {"angle": -22.5, "axis": "z", "origin": [1.26733, 1.82178, 1.66337]},
			"faces": {
				"north": {"uv": [4.46154, 6.15385, 4.61539, 5.23077], "rotation": 180, "texture": "#texture"},
				"east": {"uv": [11.38462, 14.61539, 12.30769, 8.92308], "rotation": 90, "texture": "#texture"},
				"south": {"uv": [4.46154, 6.15385, 4.61539, 5.23077], "rotation": 180, "texture": "#texture"},
				"west": {"uv": [4.30769, 8.76923, 5.07692, 3.07692], "rotation": 90, "texture": "#texture"},
				"up": {"uv": [4.46154, 8.76923, 4.61539, 3.07692], "rotation": 180, "texture": "#texture"},
				"down": {"uv": [4.46154, 8.76923, 4.61539, 3.07692], "rotation": 180, "texture": "#texture"}
			}
		},
		{
			"from": [1.5562, 0.287, 1.6634],
			"to": [1.87303, 2.10878, 14.01984],
			"rotation": {"angle": 22.5, "axis": "z", "origin": [1.90099, 0.55446, 1.66337]},
			"faces": {
				"north": {"uv": [4.46154, 5.84615, 4.61539, 5.23077], "texture": "#texture"},
				"east": {"uv": [10.76923, 14.61539, 11.53846, 8.92308], "rotation": 270, "texture": "#texture"},
				"south": {"uv": [4.46154, 5.84615, 4.61539, 5.23077], "texture": "#texture"},
				"west": {"uv": [4.30769, 8.76923, 5.07692, 3.07692], "rotation": 270, "texture": "#texture"},
				"down": {"uv": [4.46154, 8.76923, 4.61539, 3.07692], "rotation": 90, "texture": "#texture"}
			}
		},
		{
			"from": [1.9967, 0.4917, 1.9967],
			"to": [10.33003, 3.15837, 13.66337],
			"faces": {
				"north": {"uv": [8.46154, 8.92308, 4.46154, 10.30769], "texture": "#texture"},
				"east": {"uv": [8.92308, 3.23077, 10.30769, 8.61539], "rotation": 270, "texture": "#texture"},
				"south": {"uv": [4.46154, 8.92308, 8.46154, 10.30769], "texture": "#texture"},
				"west": {"uv": [12.30769, 14.30769, 13.69231, 8.92308], "rotation": 90, "texture": "#texture"},
				"up": {"uv": [2, 2, 10.33333, 13.66667], "texture": "#texture"}
			}
		},
		{
			"from": [3.6667, 1.6667, 6],
			"to": [7.6667, 3.33337, 10],
			"rotation": {"angle": 22.5, "axis": "z", "origin": [3.66667, 1.66667, 6]},
			"faces": {
				"north": {"uv": [2, 0, 2.76923, 1.53846], "rotation": 90, "texture": "#texture"},
				"east": {"uv": [0, 1.53846, 2, 2.30769], "texture": "#texture"},
				"south": {"uv": [2, 0, 2.76923, 1.53846], "rotation": 90, "texture": "#texture"},
				"west": {"uv": [0, 1.53846, 2, 2.30769], "rotation": 90, "texture": "#texture"},
				"up": {"uv": [0, 0, 2, 1.53846], "rotation": 270, "texture": "#texture"},
				"down": {"uv": [0, 0, 2.08, 1.6], "rotation": 270, "texture": "#texture"}
			}
		},
		{
			"from": [9.9967, 0.4917, 6.6634],
			"to": [10.66337, 3.15837, 9.33007],
			"faces": {
				"north": {"uv": [9.69231, 10.30769, 10, 8.92308], "texture": "#texture"},
				"east": {"uv": [8.46154, 8.92308, 10, 10.30769], "texture": "#texture"},
				"south": {"uv": [10, 10.30769, 9.69231, 8.92308], "texture": "#texture"},
				"up": {"uv": [9.33333, 11.66667, 6, 10], "rotation": 270, "texture": "#texture"}
			}
		},
		{
			"from": [1.6634, 3.4917, 13.9967],
			"to": [10.99673, 3.4927, 15.66337],
			"rotation": {"angle": 45, "axis": "x", "origin": [1.66337, 3.49175, 13.9967]},
			"faces": {
				"up": {"uv": [0, 8.92308, 4.30769, 9.69231], "texture": "#texture"},
				"down": {"uv": [0, 9.69231, 4.30769, 8.92308], "texture": "#texture"}
			}
		},
		{
			"from": [10.9967, 3.4917, 10.5268],
			"to": [12.3461, 3.4927, 13.99668],
			"rotation": {"angle": -45, "axis": "z", "origin": [10.9967, 3.49175, 13.9967]},
			"faces": {
				"up": {"uv": [2.46154, 8.92308, 4.30769, 9.69231], "rotation": 270, "texture": "#texture"},
				"down": {"uv": [0, 1, 11.66667, 2], "rotation": 90, "texture": "#texture"}
			}
		},
		{
			"from": [1.6601, 0.1287, -0.3201],
			"to": [12.32677, 0.1297, 15.6799],
			"faces": {
				"north": {"uv": [4.33333, 4.66567, 14.33333, 4.66667], "texture": "#texture"},
				"east": {"uv": [2, 4.66567, 15.66667, 4.66667], "texture": "#texture"},
				"south": {"uv": [1.66667, 4.66567, 11.66667, 4.66667], "texture": "#texture"},
				"west": {"uv": [0.33333, 4.66567, 14, 4.66667], "texture": "#texture"},
				"up": {"uv": [10.30769, 1.23077, 15.38462, 8.46154], "texture": "#texture"},
				"down": {"uv": [10.30769, 1.23077, 15.38462, 8.46154], "texture": "#texture"}
			}
		},
		{
			"from": [9.6634, 1.4917, 9.33],
			"to": [12.99673, 1.4927, 10.99667],
			"rotation": {"angle": -22.5, "axis": "y", "origin": [9.66337, 1.49175, 9.33003]},
			"faces": {
				"north": {"uv": [3.33333, 15.33233, 6.66667, 15.33333], "texture": "#texture"},
				"east": {"uv": [5.33333, 15.33233, 7, 15.33333], "texture": "#texture"},
				"south": {"uv": [9.33333, 15.33233, 12.66667, 15.33333], "texture": "#texture"},
				"up": {"uv": [10, 8.92308, 10.76923, 10.76923], "rotation": 270, "texture": "#texture"},
				"down": {"uv": [10, 8.92308, 10.76923, 10.76923], "rotation": 270, "texture": "#texture"}
			}
		},
		{
			"from": [1.6634, 1.8251, 1.6634],
			"to": [10.99673, 3.49177, 1.6644],
			"rotation": {"angle": 45, "axis": "x", "origin": [1.66337, 3.49175, 1.66337]},
			"faces": {
				"north": {"uv": [4.48, 9.69231, 0, 10.46154], "texture": "#texture"},
				"south": {"uv": [0, 9.69231, 4.46154, 10.46154], "texture": "#texture"}
			}
		},
		{
			"from": [10.9847, 3.4717, 1.6353],
			"to": [12.3341, 3.4727, 5.10518],
			"rotation": {"angle": -45, "axis": "z", "origin": [10.98465, 3.47167, 5.10513]},
			"faces": {
				"up": {"uv": [4.15385, 9.69231, 2.30769, 10.46154], "rotation": 270, "texture": "#texture"},
				"down": {"uv": [4.15385, 9.69231, 2.30769, 10.46154], "rotation": 270, "texture": "#texture"}
			}
		},
		{
			"from": [11.2694, 0.9311, 5.6634],
			"to": [11.2704, 3.9311, 10.33007],
			"rotation": {"angle": 22.5, "axis": "z", "origin": [12.33003, 3.49175, 10.33003]},
			"faces": {
				"east": {"uv": [1.84615, 10.46154, 4.15385, 12], "texture": "#texture"},
				"west": {"uv": [4.15385, 10.46154, 1.84615, 12], "texture": "#texture"}
			}
		},
		{
			"from": [-0.3333, 1.3333, 2],
			"to": [1.33337, 1.3343, 13.66667],
			"rotation": {"angle": 22.5, "axis": "z", "origin": [-0.33333, 1.33333, 2]},
			"faces": {
				"up": {"uv": [13.69231, 8.92308, 14.46154, 14.30769], "rotation": 180, "texture": "#texture"},
				"down": {"uv": [13.69231, 14.30769, 14.46154, 8.92308], "rotation": 180, "texture": "#texture"}
			}
		}
	],
	"display": {
		"thirdperson_righthand": {
			"translation": [4, 7.25, 0]
		},
		"thirdperson_lefthand": {
			"translation": [4, 7.25, 0]
		},
		"firstperson_righthand": {
			"rotation": [0, 38, 27],
			"translation": [0, 7.5, -0.25]
		},
		"firstperson_lefthand": {
			"rotation": [0, 38, 27],
			"translation": [0, 7.5, -0.25]
		},
		"head": {
			"rotation": [0, 90, 0],
			"translation": [0, -37, -3],
			"scale": [1.5, 1.5, 1.5]
		},
		"fixed": {
			"rotation": [-90.5, 0, 0],
			"translation": [2, 0, -9.5]
		}
	}
}