{
	"__comment": "Designed by Spooky_538 with Cubik Studio - https://cubik.studio",
	"textures": {
		"0": "./tire",
		"1": "./goldblock",
		"2": "./darkoak",
		"particle": "./goldblock"
	},
	"elements": [ 	 
		{
			"__comment": "Element",
			"from": [ 5.25, 2.9, 5.25 ],
			"to": [ 10.75, 4.9, 10.75 ],
			"faces": {
				"down": { "uv": [ 0, 0, 11, 4 ], "texture": "#2" },
				"up": { "uv": [ 0, 0, 11, 11 ], "texture": "#2" },
				"north": { "uv": [ 0, 0, 11, 4 ], "texture": "#2" },
				"south": { "uv": [ 0, 0, 11, 4 ], "texture": "#2" },
				"west": { "uv": [ 0, 0, 11, 4 ], "texture": "#2" },
				"east": { "uv": [ 0, 0, 11, 4 ], "texture": "#2" }
			}
		},
		{
			"__comment": "Element",
			"from": [ 5.25, -0.09999999, 5.25 ],
			"to": [ 10.75, 1.9, 10.75 ],
			"faces": {
				"down": { "uv": [ 0, 0, 11, 4 ], "texture": "#2" },
				"up": { "uv": [ 0, 0, 11, 11 ], "texture": "#2" },
				"north": { "uv": [ 0, 0, 11, 4 ], "texture": "#2" },
				"south": { "uv": [ 0, 0, 11, 4 ], "texture": "#2" },
				"west": { "uv": [ 0, 0, 11, 4 ], "texture": "#2" },
				"east": { "uv": [ 0, 0, 11, 4 ], "texture": "#2" }
			}
		},
		{
			"__comment": "Element",
			"from": [ 2.4239, 8.3294, 6.249 ],
			"to": [ 3.9239, 10.2794, 7.499 ],
			"rotation": { "origin": [ 3.17389, 11.1794, 8.25 ], "axis": "z", "angle": 45 },
			"faces": {
				"down": { "uv": [ 4.25, 0.625, 3.5, 1.25 ], "texture": "#1" },
				"north": { "uv": [ 7.25, 3, 2.5, 10.4745 ], "texture": "#1", "rotation": 180 },
				"south": { "uv": [ 10.75, 1.125, 3.5, 8.5995 ], "texture": "#1" },
				"west": { "uv": [ 7.125, 1.125, 2, 7.599501 ], "texture": "#1" },
				"east": { "uv": [ 8.125, 1.125, 3, 8.5995 ], "texture": "#1" }
			}
		},
		{
			"__comment": "Element",
			"from": [ 12.0761, 8.3294, 6.249 ],
			"to": [ 13.5761, 10.2794, 7.499 ],
			"rotation": { "origin": [ 12.82611, 11.1794, 8.25 ], "axis": "z", "angle": -45 },
			"faces": {
				"down": { "uv": [ 3.5, 0.625, 4.25, 1.25 ], "texture": "#1" },
				"north": { "uv": [ 2.5, 3, 7.25, 10.4745 ], "texture": "#1", "rotation": 180 },
				"south": { "uv": [ 3.5, 1.125, 10.75, 8.5995 ], "texture": "#1" },
				"west": { "uv": [ 3, 1.125, 8.125, 8.5995 ], "texture": "#1" },
				"east": { "uv": [ 2, 1.125, 7.125, 7.599501 ], "texture": "#1" }
			}
		},
		{
			"__comment": "Element",
			"from": [ 2.4239, 8.3294, 8.499 ],
			"to": [ 3.9239, 10.2794, 9.749 ],
			"rotation": { "origin": [ 3.17389, 11.1794, 10.5 ], "axis": "z", "angle": 45 },
			"faces": {
				"down": { "uv": [ 4.25, 0.625, 3.5, 1.25 ], "texture": "#1" },
				"north": { "uv": [ 7.25, 3, 2.5, 10.4745 ], "texture": "#1", "rotation": 180 },
				"south": { "uv": [ 10.75, 1.125, 3.5, 8.5995 ], "texture": "#1" },
				"west": { "uv": [ 7.125, 1.125, 2, 7.599501 ], "texture": "#1" },
				"east": { "uv": [ 8.125, 1.125, 3, 8.5995 ], "texture": "#1" }
			}
		},
		{
			"__comment": "Element",
			"from": [ 12.0761, 8.3294, 8.499 ],
			"to": [ 13.5761, 10.2794, 9.749 ],
			"rotation": { "origin": [ 12.82611, 11.1794, 10.5 ], "axis": "z", "angle": -45 },
			"faces": {
				"down": { "uv": [ 3.5, 0.625, 4.25, 1.25 ], "texture": "#1" },
				"north": { "uv": [ 2.5, 3, 7.25, 10.4745 ], "texture": "#1", "rotation": 180 },
				"south": { "uv": [ 3.5, 1.125, 10.75, 8.5995 ], "texture": "#1" },
				"west": { "uv": [ 3, 1.125, 8.125, 8.5995 ], "texture": "#1" },
				"east": { "uv": [ 2, 1.125, 7.125, 7.599501 ], "texture": "#1" }
			}
		},
		{
			"__comment": "Element",
			"from": [ 2.1739, 10.0794, 8.399 ],
			"to": [ 4.1739, 10.7294, 9.849 ],
			"rotation": { "origin": [ 3.17389, 11.1794, 10.5 ], "axis": "z", "angle": 45 },
			"faces": {
				"down": { "uv": [ 16, 1.125, 9, 3.948999 ], "texture": "#2" },
				"up": { "uv": [ 9, 13.949, 16, 1.125 ], "texture": "#2", "rotation": 90 },
				"north": { "uv": [ 16, 1.125, 9, 3.948999 ], "texture": "#2" },
				"south": { "uv": [ 16, 1.125, 7, 3.948999 ], "texture": "#2" },
				"west": { "uv": [ 16, 1.125, 9, 3.948999 ], "texture": "#2" },
				"east": { "uv": [ 16, 1.125, 9, 3.948999 ], "texture": "#2" }
			}
		},
		{
			"__comment": "Element",
			"from": [ 11.8261, 10.0794, 8.399 ],
			"to": [ 13.8261, 10.7294, 9.849 ],
			"rotation": { "origin": [ 12.82611, 11.1794, 10.5 ], "axis": "z", "angle": -45 },
			"faces": {
				"down": { "uv": [ 9, 1.125, 16, 3.948999 ], "texture": "#2" },
				"up": { "uv": [ 9, 1.125, 16, 13.949 ], "texture": "#2", "rotation": 90 },
				"north": { "uv": [ 9, 1.125, 16, 3.948999 ], "texture": "#2" },
				"south": { "uv": [ 7, 1.125, 16, 3.948999 ], "texture": "#2" },
				"west": { "uv": [ 9, 1.125, 16, 3.948999 ], "texture": "#2" },
				"east": { "uv": [ 9, 1.125, 16, 3.948999 ], "texture": "#2" }
			}
		},
		{
			"__comment": "Element",
			"from": [ 2.1739, 10.0794, 6.149 ],
			"to": [ 4.1739, 10.7294, 7.599 ],
			"rotation": { "origin": [ 3.17389, 11.1794, 8.25 ], "axis": "z", "angle": 45 },
			"faces": {
				"down": { "uv": [ 16, 1.125, 9, 3.948999 ], "texture": "#2" },
				"up": { "uv": [ 9, 13.949, 16, 1.125 ], "texture": "#2", "rotation": 90 },
				"north": { "uv": [ 16, 1.125, 9, 3.948999 ], "texture": "#2" },
				"south": { "uv": [ 16, 1.125, 7, 3.948999 ], "texture": "#2" },
				"west": { "uv": [ 16, 1.125, 9, 3.948999 ], "texture": "#2" },
				"east": { "uv": [ 16, 1.125, 9, 3.948999 ], "texture": "#2" }
			}
		},
		{
			"__comment": "Element",
			"from": [ 11.8261, 10.0794, 6.149 ],
			"to": [ 13.8261, 10.7294, 7.599 ],
			"rotation": { "origin": [ 12.82611, 11.1794, 8.25 ], "axis": "z", "angle": -45 },
			"faces": {
				"down": { "uv": [ 9, 1.125, 16, 3.948999 ], "texture": "#2" },
				"up": { "uv": [ 9, 1.125, 16, 13.949 ], "texture": "#2", "rotation": 90 },
				"north": { "uv": [ 9, 1.125, 16, 3.948999 ], "texture": "#2" },
				"south": { "uv": [ 7, 1.125, 16, 3.948999 ], "texture": "#2" },
				"west": { "uv": [ 9, 1.125, 16, 3.948999 ], "texture": "#2" },
				"east": { "uv": [ 9, 1.125, 16, 3.948999 ], "texture": "#2" }
			}
		},
		{
			"__comment": "Element",
			"from": [ 5.75, 4.1, 6.25 ],
			"to": [ 7.25, 9.8, 7.5 ],
			"rotation": { "origin": [ 6.75, 5.9, 8.25 ], "axis": "z", "angle": 22.5 },
			"faces": {
				"up": { "uv": [ 3.75, 1.125, 3, 1.75 ], "texture": "#1" },
				"north": { "uv": [ 6.25, 1.125, 2.5, 15.4745 ], "texture": "#1" },
				"south": { "uv": [ 11.75, 3.5, 5, 14.3495 ], "texture": "#1" },
				"west": { "uv": [ 6.125, 1.5, 3, 14.3495 ], "texture": "#1" },
				"east": { "uv": [ 8.125, 1.125, 3, 13.4745 ], "texture": "#1" }
			}
		},
		{
			"__comment": "Element",
			"from": [ 8.75, 4.1, 6.25 ],
			"to": [ 10.25, 9.8, 7.5 ],
			"rotation": { "origin": [ 9.25, 5.9, 8.25 ], "axis": "z", "angle": -22.5 },
			"faces": {
				"up": { "uv": [ 3, 1.125, 3.75, 1.75 ], "texture": "#1" },
				"north": { "uv": [ 2.5, 1.125, 6.25, 15.4745 ], "texture": "#1" },
				"south": { "uv": [ 5, 3.5, 11.75, 14.3495 ], "texture": "#1" },
				"west": { "uv": [ 3, 1.125, 8.125, 13.4745 ], "texture": "#1" },
				"east": { "uv": [ 3, 1.5, 6.125, 14.3495 ], "texture": "#1" }
			}
		},
		{
			"__comment": "Element",
			"from": [ 5.75, 4.1, 8.5 ],
			"to": [ 7.25, 9.8, 9.75 ],
			"rotation": { "origin": [ 6.75, 5.9, 10.5 ], "axis": "z", "angle": 22.5 },
			"faces": {
				"up": { "uv": [ 3.75, 1.125, 3, 1.75 ], "texture": "#1" },
				"north": { "uv": [ 6.25, 1.125, 2.5, 15.4745 ], "texture": "#1" },
				"south": { "uv": [ 11.75, 3.5, 5, 14.3495 ], "texture": "#1" },
				"west": { "uv": [ 6.125, 1.5, 3, 14.3495 ], "texture": "#1" },
				"east": { "uv": [ 8.125, 1.125, 3, 13.4745 ], "texture": "#1" }
			}
		},
		{
			"__comment": "Element",
			"from": [ 8.75, 4.1, 8.5 ],
			"to": [ 10.25, 9.8, 9.75 ],
			"rotation": { "origin": [ 9.25, 5.9, 10.5 ], "axis": "z", "angle": -22.5 },
			"faces": {
				"up": { "uv": [ 3, 1.125, 3.75, 1.75 ], "texture": "#1" },
				"north": { "uv": [ 2.5, 1.125, 6.25, 15.4745 ], "texture": "#1" },
				"south": { "uv": [ 5, 3.5, 11.75, 14.3495 ], "texture": "#1" },
				"west": { "uv": [ 3, 1.125, 8.125, 13.4745 ], "texture": "#1" },
				"east": { "uv": [ 3, 1.5, 6.125, 14.3495 ], "texture": "#1" }
			}
		},
		{
			"__comment": "Element",
			"from": [ 5.5, 1.4, 5.5 ],
			"to": [ 10.5, 3.9, 10.5 ],
			"faces": {
				"north": { "uv": [ 0, 6.25, 16, 16 ], "texture": "#1" },
				"south": { "uv": [ 0, 6.25, 16, 16 ], "texture": "#1" },
				"west": { "uv": [ 0, 6.25, 16, 16 ], "texture": "#1" },
				"east": { "uv": [ 0, 6.25, 16, 16 ], "texture": "#1" }
			}
		},
		{
			"__comment": "Element",
			"from": [ 7.4033, 12.6, 7 ],
			"to": [ 8.596779, 14.6, 9 ],
			"faces": {
				"down": { "uv": [ 6.5, 7.5, 6, 9 ], "texture": "#0" },
				"up": { "uv": [ 7.5, 6, 7, 4.5 ], "texture": "#0" },
				"north": { "uv": [ 5.5, 8.5, 6, 9.5 ], "texture": "#0" },
				"south": { "uv": [ 7, 8.5, 7.5, 9.5 ], "texture": "#0" }
			}
		},
		{
			"__comment": "Element",
			"from": [ 7.4033, 8.599999, 7 ],
			"to": [ 8.596779, 10.6, 9 ],
			"faces": {
				"down": { "uv": [ 7.5, 6, 7, 4.5 ], "texture": "#0", "rotation": 180 },
				"up": { "uv": [ 6.5, 7.5, 6, 9 ], "texture": "#0", "rotation": 180 },
				"north": { "uv": [ 5.5, 8.5, 6, 9.5 ], "texture": "#0", "rotation": 180 },
				"south": { "uv": [ 7, 8.5, 7.5, 9.5 ], "texture": "#0", "rotation": 180 }
			}
		},
		{
			"__comment": "Element",
			"from": [ 5, 11.0033, 7 ],
			"to": [ 7, 12.19678, 9 ],
			"faces": {
				"north": { "uv": [ 5.5, 8.5, 6, 9.5 ], "texture": "#0", "rotation": 90 },
				"south": { "uv": [ 7, 8.5, 7.5, 9.5 ], "texture": "#0", "rotation": 270 },
				"west": { "uv": [ 7.5, 6, 7, 4.5 ], "texture": "#0", "rotation": 270 },
				"east": { "uv": [ 6.5, 7.5, 6, 9 ], "texture": "#0", "rotation": 270 }
			}
		},
		{
			"__comment": "Element",
			"from": [ 9, 11.0033, 7 ],
			"to": [ 11, 12.19678, 9 ],
			"faces": {
				"north": { "uv": [ 5.5, 8.5, 6, 9.5 ], "texture": "#0", "rotation": 270 },
				"south": { "uv": [ 7, 8.5, 7.5, 9.5 ], "texture": "#0", "rotation": 90 },
				"west": { "uv": [ 6.5, 7.5, 6, 9 ], "texture": "#0", "rotation": 90 },
				"east": { "uv": [ 7.5, 6, 7, 4.5 ], "texture": "#0", "rotation": 90 }
			}
		},
		{
			"__comment": "Element",
			"from": [ 6.8584, 11.7845, 7 ],
			"to": [ 8.05187, 13.7845, 9 ],
			"rotation": { "origin": [ 6.74317, 11.85, 8 ], "axis": "z", "angle": 45 },
			"faces": {
				"down": { "uv": [ 6.5, 7.5, 6, 9 ], "texture": "#0" },
				"up": { "uv": [ 7.5, 6, 7, 4.5 ], "texture": "#0" },
				"north": { "uv": [ 5.5, 8.5, 6, 9.5 ], "texture": "#0" },
				"south": { "uv": [ 7, 8.5, 7.5, 9.5 ], "texture": "#0" }
			}
		},
		{
			"__comment": "Element",
			"from": [ 7.9482, 9.4155, 7 ],
			"to": [ 9.14167, 11.4155, 9 ],
			"rotation": { "origin": [ 9.25683, 11.35, 8 ], "axis": "z", "angle": 45 },
			"faces": {
				"down": { "uv": [ 7.5, 6, 7, 4.5 ], "texture": "#0", "rotation": 180 },
				"up": { "uv": [ 6.5, 7.5, 6, 9 ], "texture": "#0", "rotation": 180 },
				"north": { "uv": [ 5.5, 8.5, 6, 9.5 ], "texture": "#0", "rotation": 180 },
				"south": { "uv": [ 7, 8.5, 7.5, 9.5 ], "texture": "#0", "rotation": 180 }
			}
		},
		{
			"__comment": "Element",
			"from": [ 7.2119, 9.5619, 7 ],
			"to": [ 8.40538, 11.5619, 9 ],
			"rotation": { "origin": [ 6.74317, 11.85, 8 ], "axis": "z", "angle": -45 },
			"faces": {
				"down": { "uv": [ 7.5, 6, 7, 4.5 ], "texture": "#0", "rotation": 180 },
				"up": { "uv": [ 6.5, 7.5, 6, 9 ], "texture": "#0", "rotation": 180 },
				"north": { "uv": [ 5.5, 8.5, 6, 9.5 ], "texture": "#0", "rotation": 180 },
				"south": { "uv": [ 7, 8.5, 7.5, 9.5 ], "texture": "#0", "rotation": 180 }
			}
		},
		{
			"__comment": "Element",
			"from": [ 9.5449, 11.8188, 7 ],
			"to": [ 11.5449, 13.01227, 9 ],
			"rotation": { "origin": [ 9.25683, 11.35, 8 ], "axis": "z", "angle": 45 },
			"faces": {
				"north": { "uv": [ 5.5, 8.5, 6, 9.5 ], "texture": "#0", "rotation": 270 },
				"south": { "uv": [ 7, 8.5, 7.5, 9.5 ], "texture": "#0", "rotation": 90 },
				"west": { "uv": [ 6.5, 7.5, 6, 9 ], "texture": "#0", "rotation": 90 },
				"east": { "uv": [ 7.5, 6, 7, 4.5 ], "texture": "#0", "rotation": 90 }
			}
		},
		{
			"__comment": "Element",
			"from": [ 7.2119, 12.1381, 7.001 ],
			"to": [ 8.40538, 14.1381, 9.001 ],
			"rotation": { "origin": [ 6.74317, 11.85, 8 ], "axis": "z", "angle": 22.5 },
			"faces": {
				"down": { "uv": [ 6.5, 7.5, 6, 9 ], "texture": "#0" },
				"up": { "uv": [ 7.5, 6, 7, 4.5 ], "texture": "#0" },
				"north": { "uv": [ 5.5, 8.5, 6, 9.5 ], "texture": "#0" },
				"south": { "uv": [ 7, 8.5, 7.5, 9.5 ], "texture": "#0" }
			}
		},
		{
			"__comment": "Element",
			"from": [ 7.5946, 9.0619, 7.001 ],
			"to": [ 8.78808, 11.0619, 9.001 ],
			"rotation": { "origin": [ 9.25683, 11.35, 8 ], "axis": "z", "angle": 22.5 },
			"faces": {
				"down": { "uv": [ 7.5, 6, 7, 4.5 ], "texture": "#0", "rotation": 180 },
				"up": { "uv": [ 6.5, 7.5, 6, 9 ], "texture": "#0", "rotation": 180 },
				"north": { "uv": [ 5.5, 8.5, 6, 9.5 ], "texture": "#0", "rotation": 180 },
				"south": { "uv": [ 7, 8.5, 7.5, 9.5 ], "texture": "#0", "rotation": 180 }
			}
		},
		{
			"__comment": "Element",
			"from": [ 4.8087, 10.5413, 7.001 ],
			"to": [ 6.8087, 11.73478, 9.001 ],
			"rotation": { "origin": [ 6.74317, 11.85, 8 ], "axis": "z", "angle": 22.5 },
			"faces": {
				"north": { "uv": [ 5.5, 8.5, 6, 9.5 ], "texture": "#0", "rotation": 90 },
				"south": { "uv": [ 7, 8.5, 7.5, 9.5 ], "texture": "#0", "rotation": 270 },
				"west": { "uv": [ 7.5, 6, 7, 4.5 ], "texture": "#0", "rotation": 270 },
				"east": { "uv": [ 6.5, 7.5, 6, 9 ], "texture": "#0", "rotation": 270 }
			}
		},
		{
			"__comment": "Element",
			"from": [ 9.191299, 11.4652, 7.001 ],
			"to": [ 11.1913, 12.65868, 9.001 ],
			"rotation": { "origin": [ 9.25683, 11.35, 8 ], "axis": "z", "angle": 22.5 },
			"faces": {
				"north": { "uv": [ 5.5, 8.5, 6, 9.5 ], "texture": "#0", "rotation": 270 },
				"south": { "uv": [ 7, 8.5, 7.5, 9.5 ], "texture": "#0", "rotation": 90 },
				"west": { "uv": [ 6.5, 7.5, 6, 9 ], "texture": "#0", "rotation": 90 },
				"east": { "uv": [ 7.5, 6, 7, 4.5 ], "texture": "#0", "rotation": 90 }
			}
		},
		{
			"__comment": "Element",
			"from": [ 5, 11.5033, 7.001 ],
			"to": [ 7, 12.69678, 9.001 ],
			"rotation": { "origin": [ 6.74317, 11.85, 8 ], "axis": "z", "angle": -22.5 },
			"faces": {
				"north": { "uv": [ 5.5, 8.5, 6, 9.5 ], "texture": "#0", "rotation": 90 },
				"south": { "uv": [ 7, 8.5, 7.5, 9.5 ], "texture": "#0", "rotation": 270 },
				"west": { "uv": [ 7.5, 6, 7, 4.5 ], "texture": "#0", "rotation": 270 },
				"east": { "uv": [ 6.5, 7.5, 6, 9 ], "texture": "#0", "rotation": 270 }
			}
		},
		{
			"__comment": "Element",
			"from": [ 9, 10.5033, 7.001 ],
			"to": [ 11, 11.69678, 9.001 ],
			"rotation": { "origin": [ 9.25683, 11.35, 8 ], "axis": "z", "angle": -22.5 },
			"faces": {
				"north": { "uv": [ 5.5, 8.5, 6, 9.5 ], "texture": "#0", "rotation": 270 },
				"south": { "uv": [ 7, 8.5, 7.5, 9.5 ], "texture": "#0", "rotation": 90 },
				"west": { "uv": [ 6.5, 7.5, 6, 9 ], "texture": "#0", "rotation": 90 },
				"east": { "uv": [ 7.5, 6, 7, 4.5 ], "texture": "#0", "rotation": 90 }
			}
		},
		{
			"__comment": "Element",
			"from": [ 7.4033, 9.099999, 7.001 ],
			"to": [ 8.596779, 11.1, 9.001 ],
			"rotation": { "origin": [ 6.74317, 11.85, 8 ], "axis": "z", "angle": -22.5 },
			"faces": {
				"down": { "uv": [ 7.5, 6, 7, 4.5 ], "texture": "#0", "rotation": 180 },
				"up": { "uv": [ 6.5, 7.5, 6, 9 ], "texture": "#0", "rotation": 180 },
				"north": { "uv": [ 5.5, 8.5, 6, 9.5 ], "texture": "#0", "rotation": 180 },
				"south": { "uv": [ 7, 8.5, 7.5, 9.5 ], "texture": "#0", "rotation": 180 }
			}
		},
		{
			"__comment": "Element",
			"from": [ 7.4033, 12.1, 7.001 ],
			"to": [ 8.596779, 14.1, 9.001 ],
			"rotation": { "origin": [ 9.25683, 11.35, 8 ], "axis": "z", "angle": -22.5 },
			"faces": {
				"down": { "uv": [ 6.5, 7.5, 6, 9 ], "texture": "#0" },
				"up": { "uv": [ 7.5, 6, 7, 4.5 ], "texture": "#0" },
				"north": { "uv": [ 5.5, 8.5, 6, 9.5 ], "texture": "#0" },
				"south": { "uv": [ 7, 8.5, 7.5, 9.5 ], "texture": "#0" }
			}
		}
	],
	"display": {
		"thirdperson_righthand": {
			"rotation":  [ 60.75, 0, -4.5 ],
			"translation":  [ 0, 2.75, 3.75 ]
		},
		"thirdperson_lefthand": {
			"rotation":  [ 60.75, 0, -4.5 ],
			"translation":  [ 0, 2.75, 3.75 ]
		},
		"firstperson_righthand": {
			"rotation":  [ 0, -13, 0 ],
			"translation":  [ 0.75, 3.75, 0.25 ],
			"scale":  [ 0.67383, 0.67383, 0.67383 ]
		},
		"firstperson_lefthand": {
			"rotation":  [ 0, -13, 0 ],
			"translation":  [ 0.75, 3.75, 0.25 ],
			"scale":  [ 0.67383, 0.67383, 0.67383 ]
		},
		"gui": {
			"rotation":  [ 30, -25, 0 ],
			"translation":  [ 0, 1.5, 0 ]
		},
		"head": {
			"scale":  [ 1.5, 1.5, 1.5 ]
		},
		"ground": {
			"scale":  [ 0.42773, 0.42773, 0.42773 ]
		},
		"fixed": {
			"translation":  [ 0, 0.5, -0.25 ],
			"scale":  [ 1.18359, 1.18359, 1.18359 ]
		}
	}
}